project_euler_utils/__init__.py
project_euler_utils/helpers.py
project_euler_utils/project_euler_utils.py
project_euler_utils-0.3.2.dist-info/LICENSE
project_euler_utils-0.3.2.dist-info/METADATA
project_euler_utils-0.3.2.dist-info/WHEEL
project_euler_utils-0.3.2.dist-info/top_level.txt
project_euler_utils-0.3.2.dist-info/RECORD
