Metadata-Version: 2.2
Name: project_euler_utils
Version: 0.3.2
Summary: Utility functions to solve project-euler and math problems
Author: Shlok Kothari
Requires-Python: >=3.1
License-File: LICENSE
Requires-Dist: numpy>=2.0
Dynamic: author
Dynamic: description
Dynamic: description-content-type
Dynamic: requires-dist
Dynamic: requires-python
Dynamic: summary
